[
  {
    "MaxMobAmount": 3,
    "SpawnCooldown": 7.0,
    "Type": 1,
    "LevelNumber": 1,
    "GemsPerLevel": 0,
    "MobsData": [
      {
        "MobId": "Swordsman_1",
        "Level": 1,
        "TotalAmount": 6
      }
    ],
    "Destiny": {
      "IdDestiny": null,
      "Level": 0
    },
    "IsSafePoint": false
  },
  {
    "MaxMobAmount": 4,
    "SpawnCooldown": 6.0,
    "Type": 1,
    "LevelNumber": 2,
    "GemsPerLevel": 50,
    "MobsData": [
      {
        "MobId": "Swordsman_1",
        "Level": 1,
        "TotalAmount": 6
      },
      {
        "MobId": "Swordsman_2",
        "Level": 1,
        "TotalAmount": 3
      }
    ],
    "Destiny": {
      "IdDestiny": null,
      "Level": 0
    },
    "IsSafePoint": false
  },
  {
    "MaxMobAmount": 5,
    "SpawnCooldown": 5.0,
    "Type": 1,
    "LevelNumber": 3,
    "GemsPerLevel": 0,
    "MobsData": [
      {
        "MobId": "Swordsman_1",
        "Level": 1,
        "TotalAmount": 5
      },
      {
        "MobId": "Swordsman_2",
        "Level": 2,
        "TotalAmount": 6
      },
      {
        "MobId": "Swordsman_3",
        "Level": 1,
        "TotalAmount": 7
      },
      {
        "MobId": "Gunslinger_1",
        "Level": 1,
        "TotalAmount": 3
      }
    ],
    "Destiny": {
      "IdDestiny": "G_Salesman",
      "Level": 1
    },
    "IsSafePoint": false
  },
  {
    "MaxMobAmount": 6,
    "SpawnCooldown": 5.0,
    "Type": 1,
    "LevelNumber": 4,
    "GemsPerLevel": 0,
    "MobsData": [
      {
        "MobId": "Swordsman_1",
        "Level": 1,
        "TotalAmount": 5
      },
      {
        "MobId": "Swordsman_2",
        "Level": 2,
        "TotalAmount": 6
      },
      {
        "MobId": "Swordsman_3",
        "Level": 1,
        "TotalAmount": 7
      },
      {
        "MobId": "Gunslinger_1",
        "Level": 2,
        "TotalAmount": 4
      }
    ],
    "Destiny": {
      "IdDestiny": "G_Salesman",
      "Level": 1
    },
    "IsSafePoint": false
  }
]